doppyler/__init__.py
doppyler/client.py
doppyler/const.py
doppyler/exceptions.py
doppyler/model/__init__.py
doppyler/model/alarm.py
doppyler/model/color.py
doppyler/model/doppler.py
doppyler/model/light_bar.py
doppyler/model/main_display_text.py
doppyler/model/mini_display_number.py
doppyler/model/rainbow.py
doppyler/model/smart_button.py
doppyler/model/sound.py
doppyler/model/weather.py
doppyler/model/wifi.py
doppyler-0.0.20.dist-info/METADATA
doppyler-0.0.20.dist-info/WHEEL
doppyler-0.0.20.dist-info/top_level.txt
doppyler-0.0.20.dist-info/RECORD
