Metadata-Version: 2.1
Name: doppyler
Version: 0.0.20
Summary: A library to interact with the Sandman Doppler Clock API
Home-page: https://github.com/pa-innovation/doppyler
Author: Sandman Doppler
Author-email: hi@paloaltoinnovation.com
License: UNKNOWN
Keywords: doppyler
Platform: UNKNOWN
Classifier: Development Status :: 2 - Pre-Alpha
Classifier: Intended Audience :: Developers
Classifier: License :: OSI Approved :: GNU General Public License v3 (GPLv3)
Classifier: Natural Language :: English
Classifier: Programming Language :: Python :: 3
Classifier: Programming Language :: Python :: 3.9
Classifier: Programming Language :: Python :: 3.10
Requires-Python: >=3.9
Requires-Dist: aiohttp
